<?xml version="1.0" encoding="UTF-8"?><record_update table="sp_ng_template">
    <sp_ng_template action="INSERT_OR_UPDATE">
        <id>spDropdownTreeTemplateBB</id>
        <sp_widget display_value="GDEP Brand Bar">2cca8629dbed9c9859ac6e25ca961920</sp_widget>
        <sys_class_name>sp_ng_template</sys_class_name>
        <sys_created_by>choskins</sys_created_by>
        <sys_created_on>2020-06-21 22:46:06</sys_created_on>
        <sys_customer_update>false</sys_customer_update>
        <sys_id>efcb4269db21dc9859ac6e25ca961958</sys_id>
        <sys_mod_count>17</sys_mod_count>
        <sys_name>spDropdownTreeTemplateBB</sys_name>
        <sys_package display_value="GDEP" source="470c1443db2f0858eeb32ad94b9619de">470c1443db2f0858eeb32ad94b9619de</sys_package>
        <sys_policy/>
        <sys_replace_on_upgrade>false</sys_replace_on_upgrade>
        <sys_scope display_value="GDEP">470c1443db2f0858eeb32ad94b9619de</sys_scope>
        <sys_update_name>sp_ng_template_efcb4269db21dc9859ac6e25ca961958</sys_update_name>
        <sys_updated_by>choskins</sys_updated_by>
        <sys_updated_on>2020-08-26 05:31:17</sys_updated_on>
        <template><![CDATA[<!--

These are the drop-down items that you see when the menu is clicked

-->

<a ng-if="mi.type == 'link'" title="{{mi.title}}" target="{{mi.target}}" href="{{mi.href}}" style="text-decoration: underline;font-weight: bold;">
  {{mi.title | characters:60}}
</a>
<a ng-if="mi.type == 'record' && !mi.__page" title="{{mi.short_description}}" href="?id=gdep_ticket&table={{mi.__table}}&sys_id={{mi.sys_id}}">
  <span>{{mi.short_description | characters:60}}</span>
  <span class="block color-primary text-muted">
    <span class="block" style="float: right">
      <sn-time-ago timestamp="mi.sys_updated_on" />
    </span>
    {{mi.number}}
  </span>
</a>
<a ng-if="mi.type == 'record' && mi.__page" title="{{mi.short_description}}" href="?id={{mi.__page}}&table={{mi.__table}}&sys_id={{mi.sys_id}}">
  <span>{{mi.short_description | characters:60}}</span>
  <span class="block color-primary text-muted">
    <span class="block" style="float: right">
      <sn-time-ago timestamp="mi.sys_updated_on" />
    </span>
    {{mi.number}}
  </span>
</a>
<a ng-if="mi.type == 'request'" title="{{mi.short_description}}" href="?id=gdep_ticket&table={{mi.__table}}&sys_id={{mi.sys_id}}">
  <span>{{mi.short_description | characters:60}}</span>
  <span class="block color-primary text-muted">
    <span class="block" style="float: right">
      <sn-time-ago timestamp="mi.sys_updated_on" />
    </span>
    {{mi.number}}
  </span>
</a>
<a ng-if="mi.type == 'approval'" title="{{mi.short_description}}" href="?id=gd_approval&table={{mi.__table}}&sys_id={{mi.sys_id}}">
  <span ng-if="mi.short_description">{{mi.short_description | characters:60}}</span>
  <span class="block color-primary text-muted">
    <span class="block" style="float: right">
      <sn-time-ago timestamp="mi.sys_updated_on" />
    </span>
    {{mi.number}}
  </span>
</a>

<!--this is for a sub-menu which is added at the "instance of menu" configuration -->
<a ng-if="mi.type == 'menu' && mi.items.length" title="{{mi.title}}" href="javascript:void(0)" class="menu_trigger right-caret">
  {{mi.title | characters:60}}
</a>


<sp-dropdown-tree-template-b-b ng-if="mi.type == 'menu' && mi.items.length" items="mi.items" />
]]></template>
    </sp_ng_template>
</record_update>
